transportation_tutorials/__init__.py
transportation_tutorials/choice_theory_figures.py
transportation_tutorials/data/ACS_17_5YR_B19001.csv.gz
transportation_tutorials/data/FL-BRIDGES.csv.gz
transportation_tutorials/data/FL-COUNTY-BY-DISTRICT.csv.gz
transportation_tutorials/data/FL-COUNTY-POP.csv.gz
transportation_tutorials/data/FL-COUNTY-SHAPE.tar.gz
transportation_tutorials/data/FL-COUNTY.csv.gz
transportation_tutorials/data/FL-DISTRICTS.csv.gz
transportation_tutorials/data/FL-SUBCOUNTY-SHAPE.tar.gz
transportation_tutorials/data/MTCwork.csv.gz
transportation_tutorials/data/SEFlorida_HTS_Public_Use_Dataset.tar.gz
transportation_tutorials/data/SEFlorida_HTS_Public_Use_Skims.csv.gz
transportation_tutorials/data/SEFlorida_HTS_Public_Use_Skims2.csv.gz
transportation_tutorials/data/SERPM8-BASE2015-AM_HLOAD.csv.gz
transportation_tutorials/data/SERPM8-BASE2015-HOUSEHOLDS.csv.gz
transportation_tutorials/data/SERPM8-BASE2015-PERSONS.csv.gz
transportation_tutorials/data/SERPM8-BASE2015-TOURS.csv.gz
transportation_tutorials/data/SERPM8-BASE2015-TRIPS.csv.gz
transportation_tutorials/data/SERPM8-JUPITER-AMHSKIMS.omx
transportation_tutorials/data/SERPM8-MAZDATA.tar.gz
transportation_tutorials/data/SERPM8-MAZSHAPE.tar.gz
transportation_tutorials/data/SERPM8-NETWORK.tar.gz
transportation_tutorials/data/SERPM8-TAZSHAPE.tar.gz
transportation_tutorials/data/THIS-FILE-IS-CORRUPT.csv.gz
transportation_tutorials/data/TOJ-BOUNDARY.tar.gz
transportation_tutorials/data/US-STATES.dbf.gz
transportation_tutorials/data/__init__.py
transportation_tutorials/data/data2_ca.csv
transportation_tutorials/data/diffs19.csv
transportation_tutorials/data/diffs9.csv
transportation_tutorials/data/metadata.yml
transportation_tutorials/data/tiny_idca.csv
transportation_tutorials/data/tiny_idco.csv
transportation_tutorials/data/tiny_points.csv
transportation_tutorials/files/__init__.py
transportation_tutorials/files/archives.py
transportation_tutorials/files/downloading.py
transportation_tutorials-1.1.1.dist-info/METADATA
transportation_tutorials-1.1.1.dist-info/WHEEL
transportation_tutorials-1.1.1.dist-info/top_level.txt
transportation_tutorials-1.1.1.dist-info/RECORD
