Metadata-Version: 2.1
Name: transportation-tutorials
Version: 1.1.1
Summary: UNKNOWN
Home-page: UNKNOWN
Author: UNKNOWN
Author-email: UNKNOWN
License: UNKNOWN
Platform: UNKNOWN
Requires-Dist: numpy (>=1.15)
Requires-Dist: pandas (>=0.24)
Requires-Dist: matplotlib (>=3.0)
Requires-Dist: seaborn (>=0.9.0)
Requires-Dist: geopandas (>=0.4)
Requires-Dist: networkx (>=2.2)
Requires-Dist: osmnx (>=0.9)
Requires-Dist: folium (>=0.8)
Requires-Dist: appdirs
Requires-Dist: ipython
